notojp_matplotlib/__init__.py
notojp_matplotlib/fonts/LICENSE
notojp_matplotlib/fonts/NotoSansCJKjp-Regular.otf
notojp_matplotlib-1.0.1.dist-info/METADATA
notojp_matplotlib-1.0.1.dist-info/WHEEL
notojp_matplotlib-1.0.1.dist-info/RECORD
